{
    "currency_format_uah": "{0} грн",
    "items_count_format": "{0}  шт.",

    "auth_input_first_name": "Iм'я",
    "auth_input_last_name": "Прiзвище",
    "auth_bt_sign_in": "Увійти",
    "auth_bt_sign_up": "Вiдправити",
    "auth_input_email": "Пошта",
    "auth_input_pwd": "Пароль",
    "auth_input_invalid_email": "Не буває такої пошти",
    "auth_input_empty_field": "Обов`язкове поле",
    "auth_input_pwd_short": "Щось мавловато",
    "auth_input_pwd_long": "Ще довше не було там?",
    "auth_input_name_short": "Мало букв",
    "auth_input_name_long": "Багато букв",
    "auth_input_invalid_character": "Незрозумілі символи",

    "meal_card_bt_add": "додати",
    "meal_card_bt_remove": "прибрати",
    "checkout_message_no_orders": "Ви ще нічого не замовили",
    "checkout_bt_send": "Відправити замовлення",
    "order_success_message": "Ваше замовлення вiдісланно",

    "top_bar_bt_order": "Замовлення",
    "top_bar_bt_checkout": "Оформити",
    "top_bar_bt_sign_in": "Увійти",
    "top_bar_bt_sign_up": "Зареєструватися",
    "top_bar_bt_logout": "Вийти ({0})",

    "server_error": "помилка на сервері",
    "network_error": "немає зв'язку",
    "authorization_failed": "Шось не підходе"
}